ccs_digitalmarketplace_apiclient-37.14.0.dist-info/licenses/LICENCE
dmapiclient/__init__.py
dmapiclient/antivirus.py
dmapiclient/audit.py
dmapiclient/base.py
dmapiclient/central_digital_platform.py
dmapiclient/data.py
dmapiclient/data_insights.py
dmapiclient/errors.py
dmapiclient/exceptions.py
dmapiclient/py.typed
dmapiclient/search.py
dmapiclient/tasks.py
ccs_digitalmarketplace_apiclient-37.14.0.dist-info/METADATA
ccs_digitalmarketplace_apiclient-37.14.0.dist-info/WHEEL
ccs_digitalmarketplace_apiclient-37.14.0.dist-info/top_level.txt
ccs_digitalmarketplace_apiclient-37.14.0.dist-info/RECORD
