Metadata-Version: 2.4
Name: ccs-digitalmarketplace-apiclient
Version: 37.14.0
Summary: API clients for Digital Marketplace Data API and Search API.
Author: GDS Developers, CCS Developers
Project-URL: Homepage, https://github.com/Crown-Commercial-Service/ccs-digitalmarketplace-apiclient
Project-URL: Repository, https://github.com/Crown-Commercial-Service/ccs-digitalmarketplace-apiclient.git
Project-URL: Issues, https://github.com/Crown-Commercial-Service/ccs-digitalmarketplace-apiclient/issues
Project-URL: Changelog, https://github.com/Crown-Commercial-Service/ccs-digitalmarketplace-apiclient/CHANGELOG.md
Requires-Python: <3.15,>=3.11
License-File: LICENCE
Requires-Dist: requests<3,>=2.18.4
Requires-Dist: Flask>=3.0.3
Provides-Extra: dev
Requires-Dist: ruff==0.14.13; extra == "dev"
Requires-Dist: mypy==1.19.1; extra == "dev"
Requires-Dist: pytest==9.0.2; extra == "dev"
Requires-Dist: pytest-cov==7.0.0; extra == "dev"
Requires-Dist: requests-mock==1.12.1; extra == "dev"
Requires-Dist: types-requests; extra == "dev"
Requires-Dist: pre-commit==4.5.1; extra == "dev"
Requires-Dist: ccs-digitalmarketplace-test-utils==7.7.0; extra == "dev"
Dynamic: license-file
